Metadata-Version: 2.1
Name: lsg
Version: 0.1.0
Summary: A better alias for `ls | grep`
Home-page: https://gitlab.com/justinethomas/lsg
Author: Justine T Kizhakkinedath
Author-email: justine@kizhak.com
License: UNKNOWN
Project-URL: Bug Reports, https://gitlab.com/justinekizhak/lsg/issues
Project-URL: Say Thanks!, http://saythanks.io/to/justinekizhak
Project-URL: Source, https://gitlab.com/justinekizhak/lsg
Keywords: command-line tool search files and folders
Platform: UNKNOWN
Classifier: Development Status :: 4 - Beta
Classifier: Intended Audience :: Developers
Classifier: Programming Language :: Python :: 3.6
Classifier: License :: OSI Approved :: MIT License
Classifier: Operating System :: OS Independent
